odoo8_addon_partner_tag_actions-8.0.1.0.0-py2.7-nspkg.pth
odoo8_addon_partner_tag_actions-8.0.1.0.0.dist-info/DESCRIPTION.rst
odoo8_addon_partner_tag_actions-8.0.1.0.0.dist-info/METADATA
odoo8_addon_partner_tag_actions-8.0.1.0.0.dist-info/RECORD
odoo8_addon_partner_tag_actions-8.0.1.0.0.dist-info/WHEEL
odoo8_addon_partner_tag_actions-8.0.1.0.0.dist-info/metadata.json
odoo8_addon_partner_tag_actions-8.0.1.0.0.dist-info/namespace_packages.txt
odoo8_addon_partner_tag_actions-8.0.1.0.0.dist-info/top_level.txt
odoo_addons/partner_tag_actions/README.rst
odoo_addons/partner_tag_actions/__init__.py
odoo_addons/partner_tag_actions/__openerp__.py
odoo_addons/partner_tag_actions/data/partner_action_data.xml
odoo_addons/partner_tag_actions/i18n/fr.po
odoo_addons/partner_tag_actions/i18n/partner_tag_actions.pot
odoo_addons/partner_tag_actions/models/__init__.py
odoo_addons/partner_tag_actions/models/partner.py
odoo_addons/partner_tag_actions/models/partner_action.py
odoo_addons/partner_tag_actions/models/partner_action_type.py
odoo_addons/partner_tag_actions/security/ir.model.access.csv
odoo_addons/partner_tag_actions/security/res_groups_data.xml
odoo_addons/partner_tag_actions/static/description/icon.png
odoo_addons/partner_tag_actions/tests/__init__.py
odoo_addons/partner_tag_actions/tests/test_partner_action.py
odoo_addons/partner_tag_actions/views/partner_action_type_view.xml
odoo_addons/partner_tag_actions/views/partner_action_view.xml
odoo_addons/partner_tag_actions/views/partner_view.xml
